tinyurls/__init__.py
tinyurls/models.py
tinyurls/service.py
tinyurls/settings.py
tinyurls-0.0.3.data/scripts/tinyurls
tinyurls-0.0.3.dist-info/METADATA
tinyurls-0.0.3.dist-info/RECORD
tinyurls-0.0.3.dist-info/WHEEL
tinyurls-0.0.3.dist-info/top_level.txt
