Metadata-Version: 2.1
Name: tinyurls
Version: 0.0.3
Summary: URL shortening service to be used in a microservices environment.
Home-page: https://github.com/rangertaha/tinyurls
Author: rangertaha
Author-email: rangertaha@gmail.com
License: MIT
Platform: UNKNOWN
Classifier: License :: OSI Approved :: MIT License
Classifier: Programming Language :: Python :: 3
Classifier: Programming Language :: Python :: 3.4
Classifier: Programming Language :: Python :: 3.5
Classifier: Programming Language :: Python :: 3.6
Classifier: Programming Language :: Python :: Implementation :: CPython
Classifier: Programming Language :: Python :: Implementation :: PyPy
Requires-Dist: tornado
Requires-Dist: SQLAlchemy
Requires-Dist: validators
Requires-Dist: fluent
Requires-Dist: pycodestyle
Requires-Dist: prometheus-client
